{
  "name": "drzewo_lisciaste_2",
  "category": "forest",
  "grid_size": 64,
  "bounds": {
    "row_min": 14,
    "row_max": 43,
    "col_min": 21,
    "col_max": 56
  },
  "origin": {
    "row": 14,
    "col": 21
  },
  "size": {
    "rows": 30,
    "cols": 36
  },
  "hotspot": {
    "row": 29.0,
    "col": 39.0
  },
  "created_at": "2025-10-19T17:23:59",
  "source_hex": "15,0",
  "image": "terrain\\presets\\user_assets\\forest\\drzewo_lisciaste_2.png",
  "thumbnail": "terrain\\presets\\user_assets\\forest\\drzewo_lisciaste_2_thumb.png",
  "selection": {
    "type": "polygon",
    "loop": [
      {
        "row": 15,
        "col": 33
      },
      {
        "row": 15,
        "col": 32
      },
      {
        "row": 15,
        "col": 31
      },
      {
        "row": 15,
        "col": 30
      },
      {
        "row": 15,
        "col": 29
      },
      {
        "row": 16,
        "col": 28
      },
      {
        "row": 17,
        "col": 28
      },
      {
        "row": 18,
        "col": 28
      },
      {
        "row": 19,
        "col": 28
      },
      {
        "row": 20,
        "col": 28
      },
      {
        "row": 21,
        "col": 28
      },
      {
        "row": 21,
        "col": 27
      },
      {
        "row": 22,
        "col": 27
      },
      {
        "row": 22,
        "col": 28
      },
      {
        "row": 23,
        "col": 28
      },
      {
        "row": 24,
        "col": 28
      },
      {
        "row": 25,
        "col": 28
      },
      {
        "row": 25,
        "col": 27
      },
      {
        "row": 25,
        "col": 26
      },
      {
        "row": 25,
        "col": 25
      },
      {
        "row": 25,
        "col": 24
      },
      {
        "row": 26,
        "col": 23
      },
      {
        "row": 26,
        "col": 22
      },
      {
        "row": 27,
        "col": 21
      },
      {
        "row": 28,
        "col": 22
      },
      {
        "row": 29,
        "col": 22
      },
      {
        "row": 30,
        "col": 21
      },
      {
        "row": 31,
        "col": 22
      },
      {
        "row": 32,
        "col": 22
      },
      {
        "row": 33,
        "col": 22
      },
      {
        "row": 33,
        "col": 23
      },
      {
        "row": 33,
        "col": 24
      },
      {
        "row": 33,
        "col": 25
      },
      {
        "row": 33,
        "col": 26
      },
      {
        "row": 34,
        "col": 27
      },
      {
        "row": 34,
        "col": 28
      },
      {
        "row": 34,
        "col": 29
      },
      {
        "row": 35,
        "col": 30
      },
      {
        "row": 35,
        "col": 31
      },
      {
        "row": 35,
        "col": 32
      },
      {
        "row": 35,
        "col": 33
      },
      {
        "row": 35,
        "col": 34
      },
      {
        "row": 36,
        "col": 34
      },
      {
        "row": 37,
        "col": 34
      },
      {
        "row": 38,
        "col": 34
      },
      {
        "row": 39,
        "col": 34
      },
      {
        "row": 40,
        "col": 34
      },
      {
        "row": 41,
        "col": 34
      },
      {
        "row": 41,
        "col": 33
      },
      {
        "row": 41,
        "col": 32
      },
      {
        "row": 41,
        "col": 31
      },
      {
        "row": 42,
        "col": 31
      },
      {
        "row": 42,
        "col": 30
      },
      {
        "row": 42,
        "col": 29
      },
      {
        "row": 43,
        "col": 28
      },
      {
        "row": 43,
        "col": 29
      },
      {
        "row": 43,
        "col": 30
      },
      {
        "row": 43,
        "col": 31
      },
      {
        "row": 43,
        "col": 32
      },
      {
        "row": 43,
        "col": 33
      },
      {
        "row": 43,
        "col": 34
      },
      {
        "row": 43,
        "col": 35
      },
      {
        "row": 43,
        "col": 36
      },
      {
        "row": 43,
        "col": 37
      },
      {
        "row": 43,
        "col": 38
      },
      {
        "row": 43,
        "col": 39
      },
      {
        "row": 43,
        "col": 40
      },
      {
        "row": 43,
        "col": 41
      },
      {
        "row": 43,
        "col": 42
      },
      {
        "row": 43,
        "col": 43
      },
      {
        "row": 43,
        "col": 44
      },
      {
        "row": 43,
        "col": 45
      },
      {
        "row": 43,
        "col": 46
      },
      {
        "row": 43,
        "col": 47
      },
      {
        "row": 43,
        "col": 48
      },
      {
        "row": 43,
        "col": 49
      },
      {
        "row": 42,
        "col": 49
      },
      {
        "row": 41,
        "col": 49
      },
      {
        "row": 40,
        "col": 48
      },
      {
        "row": 40,
        "col": 47
      },
      {
        "row": 39,
        "col": 46
      },
      {
        "row": 40,
        "col": 45
      },
      {
        "row": 40,
        "col": 44
      },
      {
        "row": 40,
        "col": 43
      },
      {
        "row": 39,
        "col": 43
      },
      {
        "row": 38,
        "col": 43
      },
      {
        "row": 37,
        "col": 43
      },
      {
        "row": 36,
        "col": 43
      },
      {
        "row": 36,
        "col": 44
      },
      {
        "row": 35,
        "col": 45
      },
      {
        "row": 35,
        "col": 46
      },
      {
        "row": 35,
        "col": 47
      },
      {
        "row": 34,
        "col": 48
      },
      {
        "row": 33,
        "col": 49
      },
      {
        "row": 32,
        "col": 49
      },
      {
        "row": 31,
        "col": 49
      },
      {
        "row": 30,
        "col": 49
      },
      {
        "row": 29,
        "col": 49
      },
      {
        "row": 28,
        "col": 50
      },
      {
        "row": 27,
        "col": 50
      },
      {
        "row": 27,
        "col": 51
      },
      {
        "row": 27,
        "col": 52
      },
      {
        "row": 27,
        "col": 53
      },
      {
        "row": 27,
        "col": 54
      },
      {
        "row": 27,
        "col": 55
      },
      {
        "row": 26,
        "col": 56
      },
      {
        "row": 25,
        "col": 55
      },
      {
        "row": 24,
        "col": 54
      },
      {
        "row": 23,
        "col": 54
      },
      {
        "row": 22,
        "col": 53
      },
      {
        "row": 21,
        "col": 53
      },
      {
        "row": 20,
        "col": 52
      },
      {
        "row": 19,
        "col": 52
      },
      {
        "row": 19,
        "col": 51
      },
      {
        "row": 19,
        "col": 50
      },
      {
        "row": 19,
        "col": 49
      },
      {
        "row": 18,
        "col": 49
      },
      {
        "row": 17,
        "col": 49
      },
      {
        "row": 16,
        "col": 49
      },
      {
        "row": 15,
        "col": 49
      },
      {
        "row": 15,
        "col": 48
      },
      {
        "row": 15,
        "col": 47
      },
      {
        "row": 15,
        "col": 46
      },
      {
        "row": 15,
        "col": 45
      },
      {
        "row": 14,
        "col": 44
      },
      {
        "row": 14,
        "col": 43
      },
      {
        "row": 14,
        "col": 42
      },
      {
        "row": 14,
        "col": 41
      },
      {
        "row": 14,
        "col": 40
      },
      {
        "row": 14,
        "col": 39
      },
      {
        "row": 14,
        "col": 38
      },
      {
        "row": 15,
        "col": 37
      },
      {
        "row": 15,
        "col": 36
      },
      {
        "row": 15,
        "col": 35
      },
      {
        "row": 15,
        "col": 34
      }
    ],
    "cell_count": 683
  }
}